Probador_phy_tx.v
module Probador_phy_tx(
    output reg [7:0] In0,
    output reg [7:0] In1,
    output reg [7:0] In2,
    output reg [7:0] In3,
    output reg clk,
    output reg clk2,
    output reg clk4,
    output reg valid0, valid1, valid2, valid3,
    input [7:0] data_out
);

initial begin
        // Nombre de archivo del "dump"
		$dumpfile("phy_tx.vcd");

        // Directiva para "dumpear" variables	
		$dumpvars;	

        //Mux 2x1 8bits
        @(posedge clk);
        In0 <= 8'b11111111; 
        In1 <= 8'b11101110;
        In2 <= 8'b11011101;
        In3 <= 8'b11001100;
        valid0 <= 1'b1;
        valid1 <= 1'b1;
        valid2 <= 1'b1;
        valid3 <= 1'b1;
        	
       @(posedge clk);	
            
        In0 <= 8'b10111011; 
        In1 <= 8'b10101010;
        In2 <= 8'b10011001;
        In3 <= 8'b10001000; 

		@(posedge clk);

        valid0 <= 1'b0;
        valid1 <= 1'b0;
        valid3 <= 1'b0;
        In0 <= 8'b1010101; 
        In1 <= 8'b1010101;
        In2 <= 8'b1110111;
        In3 <= 8'b1010101; 
        @(posedge clk);
        valid2 <= 1'b0;
        @(posedge clk);
         //Mux 2x1 8bits
        In0 <= 8'b00000000;
        In1 <= 8'b00000000; 
        In2 <= 8'b00000000; 
        In3 <= 8'b00000000;
        // Termina de almacenar señales
		$finish;

	end

	// Reloj

    //Valor inicial del reloj para que no sea indeterminado
	initial	clk 	<= 0;
    initial	clk2 	<= 1;	
    initial	clk4 	<= 1;

    //Toggle cada 2*10 nano segundos		
	always	#8 clk 	<= ~clk;

    always  #4 clk2 <= ~clk2;

    always  #2 clk4 <= ~clk4;
    		
endmodule

Mux2x1_8Bits.v
module Mux2x1_8Bits(
    input [7:0] In0,In1,
    input clk, valid0, valid1,
    output reg outValid,
    output reg [7:0] data_out
    );

    reg [7:0] ValorAnterior;
    reg  validTemp=1'b0;
    reg selector=1'b0;

    /*initial begin
        selector = 0;
        validTemp = 0;
        ValorAnterior=8'b0;
    end*/

    always @(*)begin
        selector = 0;
        validTemp = 0;
        ValorAnterior=8'b0;
        if(valid0 == 1 & selector == 0) begin
            ValorAnterior = In0;
            validTemp = valid0;
        end

        else if(valid1 == 1 & selector == 1) begin
            ValorAnterior = In1; 
            validTemp = valid1;  
        end
        else begin
            validTemp = 0;
        end
    end  

    always @(posedge clk)begin
        selector <= selector + 1;
        data_out <= ValorAnterior;
        outValid <= validTemp;
        
    end

endmodule

phy_tx.v
`include "Mux2x1_8Bits.v"

module phy_tx(
    input [7:0] In0,
    input [7:0] In1,
    input [7:0] In2,
    input [7:0] In3,
    input clk,
    input clk2,
    input clk4,
    input valid0, valid1, valid2, valid3,
    output [7:0] data_out,
    output valid_out
);

wire [7:0] out_temp1, out_temp2;
wire valid_out_1, valid_out_2;

Mux2x1_8Bits MUX2x1_1 (
    .In0(In0),
    .In1(In1),
    .clk(clk2),
    .valid0(valid0),
    .valid1(valid1),
    .outValid(valid_out_1),
    .data_out(out_temp1)
); 

Mux2x1_8Bits MUX2x1_2 (
    .In0(In2),
    .In1(In3),
    .clk(clk2),
    .valid0(valid2),
    .valid1(valid3),
    .outValid(valid_out_2),
    .data_out(out_temp2)
); 


Mux2x1_8Bits MUX2x1_3 (
    .In0(out_temp2),
    .In1(out_temp1),
    .clk(clk4),
    .valid0(valid_out_2),
    .valid1(valid_out_1),
    .data_out(data_out),
    .outValid(valid_out)
); 


endmodule

BancoPruebas_phy_tx.v
`include "phy_tx.v"
`include "Probador_phy_tx.v"

module BancoPruebas_phy_tx;

/*AUTOWIRE*/
// Beginning of automatic wires (for undeclared instantiated-module outputs)
wire [7:0]		In0;			// From Probador_phy_tx_testbench of Probador_phy_tx.v
wire [7:0]		In1;			// From Probador_phy_tx_testbench of Probador_phy_tx.v
wire [7:0]		In2;			// From Probador_phy_tx_testbench of Probador_phy_tx.v
wire [7:0]		In3;			// From Probador_phy_tx_testbench of Probador_phy_tx.v
wire			clk;			// From Probador_phy_tx_testbench of Probador_phy_tx.v
wire			clk2;			// From Probador_phy_tx_testbench of Probador_phy_tx.v
wire			clk4;			// From Probador_phy_tx_testbench of Probador_phy_tx.v
wire [7:0]		data_out;		// From phy_tx_testbench of phy_tx.v
wire			valid0;			// From Probador_phy_tx_testbench of Probador_phy_tx.v
wire			valid1;			// From Probador_phy_tx_testbench of Probador_phy_tx.v
wire			valid2;			// From Probador_phy_tx_testbench of Probador_phy_tx.v
wire			valid3;			// From Probador_phy_tx_testbench of Probador_phy_tx.v
wire			valid_out;		// From phy_tx_testbench of phy_tx.v
// End of automatics

phy_tx phy_tx_testbench(/*AUTOINST*/
			// Outputs
			.data_out	(data_out[7:0]),
			.valid_out	(valid_out),
			// Inputs
			.In0		(In0[7:0]),
			.In1		(In1[7:0]),
			.In2		(In2[7:0]),
			.In3		(In3[7:0]),
			.clk		(clk),
			.clk2		(clk2),
			.clk4		(clk4),
			.valid0		(valid0),
			.valid1		(valid1),
			.valid2		(valid2),
			.valid3		(valid3));

Probador_phy_tx Probador_phy_tx_testbench(/*AUTOINST*/
					  // Outputs
					  .In0			(In0[7:0]),
					  .In1			(In1[7:0]),
					  .In2			(In2[7:0]),
					  .In3			(In3[7:0]),
					  .clk			(clk),
					  .clk2			(clk2),
					  .clk4			(clk4),
					  .valid0		(valid0),
					  .valid1		(valid1),
					  .valid2		(valid2),
					  .valid3		(valid3),
					  // Inputs
					  .data_out		(data_out[7:0]));


endmodule

// Local Variable:
   // eval:(verilog-read-defines)
   // eval:(verilog-read-includes)
   // End:

phy_tx.vcd
$date
	Tue May 25 01:59:16 2021
$end
$version
	Icarus Verilog
$end
$timescale
	1s
$end
$scope module BancoPruebas_phy_tx $end
$var wire 1 ! valid_out $end
$var wire 1 " valid3 $end
$var wire 1 # valid2 $end
$var wire 1 $ valid1 $end
$var wire 1 % valid0 $end
$var wire 8 & data_out [7:0] $end
$var wire 1 ' clk4 $end
$var wire 1 ( clk2 $end
$var wire 1 ) clk $end
$var wire 8 * In3 [7:0] $end
$var wire 8 + In2 [7:0] $end
$var wire 8 , In1 [7:0] $end
$var wire 8 - In0 [7:0] $end
$scope module Probador_phy_tx_testbench $end
$var wire 8 . data_out [7:0] $end
$var reg 8 / In0 [7:0] $end
$var reg 8 0 In1 [7:0] $end
$var reg 8 1 In2 [7:0] $end
$var reg 8 2 In3 [7:0] $end
$var reg 1 ) clk $end
$var reg 1 ( clk2 $end
$var reg 1 ' clk4 $end
$var reg 1 % valid0 $end
$var reg 1 $ valid1 $end
$var reg 1 # valid2 $end
$var reg 1 " valid3 $end
$upscope $end
$scope module phy_tx_testbench $end
$var wire 8 3 In0 [7:0] $end
$var wire 8 4 In1 [7:0] $end
$var wire 8 5 In2 [7:0] $end
$var wire 8 6 In3 [7:0] $end
$var wire 1 ) clk $end
$var wire 1 ( clk2 $end
$var wire 1 ' clk4 $end
$var wire 1 % valid0 $end
$var wire 1 $ valid1 $end
$var wire 1 # valid2 $end
$var wire 1 " valid3 $end
$var wire 1 7 valid_out_2 $end
$var wire 1 8 valid_out_1 $end
$var wire 1 ! valid_out $end
$var wire 8 9 out_temp2 [7:0] $end
$var wire 8 : out_temp1 [7:0] $end
$var wire 8 ; data_out [7:0] $end
$scope module MUX2x1_1 $end
$var wire 8 < In0 [7:0] $end
$var wire 8 = In1 [7:0] $end
$var wire 1 ( clk $end
$var wire 1 % valid0 $end
$var wire 1 $ valid1 $end
$var reg 8 > ValorAnterior [7:0] $end
$var reg 8 ? data_out [7:0] $end
$var reg 1 8 outValid $end
$var reg 1 @ selector $end
$var reg 1 A validTemp $end
$upscope $end
$scope module MUX2x1_2 $end
$var wire 8 B In0 [7:0] $end
$var wire 8 C In1 [7:0] $end
$var wire 1 ( clk $end
$var wire 1 # valid0 $end
$var wire 1 " valid1 $end
$var reg 8 D ValorAnterior [7:0] $end
$var reg 8 E data_out [7:0] $end
$var reg 1 7 outValid $end
$var reg 1 F selector $end
$var reg 1 G validTemp $end
$upscope $end
$scope module MUX2x1_3 $end
$var wire 8 H In0 [7:0] $end
$var wire 8 I In1 [7:0] $end
$var wire 1 ' clk $end
$var wire 1 7 valid0 $end
$var wire 1 8 valid1 $end
$var reg 8 J ValorAnterior [7:0] $end
$var reg 8 K data_out [7:0] $end
$var reg 1 ! outValid $end
$var reg 1 L selector $end
$var reg 1 M validTemp $end
$upscope $end
$upscope $end
$upscope $end
$enddefinitions $end
#0
$dumpvars
0M
1L
bx K
bx J
bx I
bx H
0G
1F
bx E
bx D
bx C
bx B
0A
1@
bx ?
bx >
bx =
bx <
bx ;
bx :
bx 9
08
07
bx 6
bx 5
bx 4
bx 3
bx 2
bx 1
bx 0
bx /
bx .
bx -
bx ,
bx +
bx *
0)
1(
1'
bx &
x%
x$
x#
x"
0!
$end
#2
0'
#4
0L
1'
0(
#6
0'
#8
1G
b11011101 D
1A
b11111111 >
1L
0F
0@
1"
1#
1$
1%
b11001100 *
b11001100 2
b11001100 6
b11001100 C
b11011101 +
b11011101 1
b11011101 5
b11011101 B
b11101110 ,
b11101110 0
b11101110 4
b11101110 =
b11111111 -
b11111111 /
b11111111 3
b11111111 <
1'
1(
1)
#10
0'
#12
0L
1'
0(
#14
0'
#16
b11101110 >
1M
b11111111 J
b11001100 D
1L
18
b11111111 :
b11111111 ?
b11111111 I
1@
17
b11011101 9
b11011101 E
b11011101 H
1F
1'
1(
0)
#18
0'
#20
b11011101 J
1!
b11111111 &
b11111111 .
b11111111 ;
b11111111 K
0L
1'
0(
#22
0'
#24
b11101110 J
b10011001 D
b10111011 >
b11011101 &
b11011101 .
b11011101 ;
b11011101 K
1L
b11001100 9
b11001100 E
b11001100 H
0F
b11101110 :
b11101110 ?
b11101110 I
0@
b10001000 *
b10001000 2
b10001000 6
b10001000 C
b10011001 +
b10011001 1
b10011001 5
b10011001 B
b10101010 ,
b10101010 0
b10101010 4
b10101010 =
b10111011 -
b10111011 /
b10111011 3
b10111011 <
1'
1(
1)
#26
0'
#28
b11001100 J
b11101110 &
b11101110 .
b11101110 ;
b11101110 K
0L
1'
0(
#30
0'
#32
b10101010 >
b10111011 J
b10001000 D
b11001100 &
b11001100 .
b11001100 ;
b11001100 K
1L
b10111011 :
b10111011 ?
b10111011 I
1@
b10011001 9
b10011001 E
b10011001 H
1F
1'
1(
0)
#34
0'
#36
b10011001 J
b10111011 &
b10111011 .
b10111011 ;
b10111011 K
0L
1'
0(
#38
0'
#40
b10101010 J
b1110111 D
0A
b10011001 &
b10011001 .
b10011001 ;
b10011001 K
1L
b10001000 9
b10001000 E
b10001000 H
0F
b10101010 :
b10101010 ?
b10101010 I
0@
b1010101 *
b1010101 2
b1010101 6
b1010101 C
b1110111 +
b1110111 1
b1110111 5
b1110111 B
b1010101 ,
b1010101 0
b1010101 4
b1010101 =
b1010101 -
b1010101 /
b1010101 3
b1010101 <
0"
0$
0%
1'
1(
1)
#42
0'
#44
b10001000 J
b10101010 &
b10101010 .
b10101010 ;
b10101010 K
0L
1'
0(
#46
0'
#48
0M
0G
b10001000 &
b10001000 .
b10001000 ;
b10001000 K
1L
08
1@
b1110111 9
b1110111 E
b1110111 H
1F
1'
1(
0)
#50
0'
#52
1M
b1110111 J
0!
0L
1'
0(
#54
0'
#56
0M
1!
b1110111 &
b1110111 .
b1110111 ;
b1110111 K
1L
07
0F
0@
0#
1'
1(
1)
#58
0'
#60
0!
0L
1'
0(
#62
0'
#64
1L
1@
1F
1'
1(
0)
#66
0'
#68
0L
1'
0(
#70
0'
#72
1L
0F
0@
b0 *
b0 2
b0 6
b0 C
b0 +
b0 1
b0 5
b0 B
b0 ,
b0 0
b0 4
b0 =
b0 -
b0 /
b0 3
b0 <
1'
1(
1)
