probadorDemux.v
module probadorDemux( // Módulo probador: generador de señales y monitor de datos
output reg clk,
output reg validIn,
output reg [7:0] data_in,
input [7:0] data_out0,
input [7:0] data_out1,
input outValid0,
input outValid1
);

	initial begin
		$dumpfile("PruebademuxJOSERolo.vcd");	
		$dumpvars;
		
		//$display ("\t\t\tclk,\tS,\tVal,\tin0,\tin1,\toutCon, \toutEstr,\tcont");
		
		//$monitor($time,"\t%b\t%b\t%b\t%b\t%b\t%b\t\t%b", clk, v);
		{data_in} =  8'b00000000;	// A los 2 bits, asigna un tipo bit con valor 0.
        {validIn} = 1'b1; 
		repeat (8) begin		
        		@(posedge clk);	// Espera/sincroniza con el flanco positivo del reloj
                
                {data_in} <= {data_in} +1;
                /*
				if(data_out_est==data_out_cond)
					checker<=1;
				else
					checker<=0;
                */
		end
		@(posedge clk);	
		{ validIn, data_in} <= 'b0;
		$finish;		
	end
	// Reloj
	initial	clk 	<= 0;	
	always	#20 clk 	<= ~clk;		// Hace "toggle" cada 20*10ns
endmodule

Demux_1x2_8Bits.v
module Demux_1x2_8Bits( 
        input [7:0] In0, 
        input clk, validIn, 
        output reg outValid0, outValid1,  
        output reg [7:0] data_out0,data_out1
        );

reg [7:0] ValorAnterior_out0;
reg [7:0] ValorAnterior_out1;
reg  validTemp_In0;
reg  validTemp_In1;
reg selector;

initial begin
        selector = 0;
end

always @(*)begin
        if(validIn == 1 && selector == 0) begin
            ValorAnterior_out0 =In0;
            validTemp_In0= validIn;

        end

        else if(validIn == 1 && selector == 1) begin
            ValorAnterior_out1 =In0;
            validTemp_In1 = validIn;
        end

end

always @(posedge clk)begin
        selector <= selector +1;       
        data_out0 <= ValorAnterior_out0;
        data_out1 <= ValorAnterior_out1;
        outValid0 <= validTemp_In0;
        outValid1 <= validTemp_In1;
end

endmodule

BancoPruebaDemux.v
`timescale 	1ns				/ 100ps
`include "Demux_1x2_8Bits.v"
`include "probadorDemux.v"


module BancoPruebaDemux; // Testbench
	// Por lo general, las señales en el banco de pruebas son wires.
	// No almacenan un valor, son manejadas por otras instancias de módulos.
	wire clk, validIn, outvalid0, outvalid1;
    wire [7:0] In0, dataout0,dataout1;


    Demux_1x2_8Bits Demux1( .In0(In0), .clk(clk), .validIn(validIn), .outValid0(outvalid0), .outValid1(outvalid1), .data_out0(dataout0),.data_out1(dataout1));
  
	probadorDemux prob( .data_in(In0), .clk(clk), .validIn(validIn), .outValid0(outvalid0), .outValid1(outvalid1), .data_out0(dataout0),.data_out1(dataout1));
 
/*
	Mux4x1_4Bits Mux4x1Conductual( .valid(valid), .selector(selector), .data_in0(data_in0), .data_in1(data_in1), .data_in2(data_in2), .data_in3(data_in3), .data_out(data_outCond));
    Mux4x1_4Bits_synth Mux4x1Estructural( .valid(valid), .selector(selector), .data_in0(data_in0), .data_in1(data_in1), .data_in2(data_in2), .data_in3(data_in3), .data_out(data_outEstr));
	probador prob(.clk(clk), .valid(valid), .selector(selector), .data_in0(data_in0), .data_in1(data_in1),.data_in2(data_in2), .data_in3(data_in3), .data_outConductual(data_outCond), .data_outExtructural(data_outEstr));
  */  

endmodule

// Local Variable:
   // eval:(verilog-read-defines)
   // eval:(verilog-read-includes)
   // End:

PruebademuxJOSERolo.vcd
$date
	Tue May 25 00:22:27 2021
$end
$version
	Icarus Verilog
$end
$timescale
	100ps
$end
$scope module BancoPruebaDemux $end
$var wire 1 ! validIn $end
$var wire 1 " outvalid1 $end
$var wire 1 # outvalid0 $end
$var wire 8 $ dataout1 [7:0] $end
$var wire 8 % dataout0 [7:0] $end
$var wire 1 & clk $end
$var wire 8 ' In0 [7:0] $end
$scope module Demux1 $end
$var wire 1 ! validIn $end
$var wire 1 & clk $end
$var wire 8 ( In0 [7:0] $end
$var reg 8 ) ValorAnterior_out0 [7:0] $end
$var reg 8 * ValorAnterior_out1 [7:0] $end
$var reg 8 + data_out0 [7:0] $end
$var reg 8 , data_out1 [7:0] $end
$var reg 1 # outValid0 $end
$var reg 1 " outValid1 $end
$var reg 1 - selector $end
$var reg 1 . validTemp_In0 $end
$var reg 1 / validTemp_In1 $end
$upscope $end
$scope module prob $end
$var wire 8 0 data_out0 [7:0] $end
$var wire 8 1 data_out1 [7:0] $end
$var wire 1 # outValid0 $end
$var wire 1 " outValid1 $end
$var reg 1 & clk $end
$var reg 8 2 data_in [7:0] $end
$var reg 1 ! validIn $end
$upscope $end
$upscope $end
$enddefinitions $end
#0
$dumpvars
b0 2
bx 1
bx 0
x/
1.
0-
bx ,
bx +
bx *
b0 )
b0 (
b0 '
0&
bx %
bx $
x#
x"
1!
$end
#200
1/
b1 *
1#
b0 %
b0 +
b0 0
1-
b1 '
b1 (
b1 2
1&
#400
0&
#600
b10 )
b10 '
b10 (
b10 2
1"
b1 $
b1 ,
b1 1
0-
1&
#800
0&
#1000
b11 *
b10 %
b10 +
b10 0
1-
b11 '
b11 (
b11 2
1&
#1200
0&
#1400
b100 )
b100 '
b100 (
b100 2
b11 $
b11 ,
b11 1
0-
1&
#1600
0&
#1800
b101 *
b100 %
b100 +
b100 0
1-
b101 '
b101 (
b101 2
1&
#2000
0&
#2200
b110 )
b110 '
b110 (
b110 2
b101 $
b101 ,
b101 1
0-
1&
#2400
0&
#2600
b111 *
b110 %
b110 +
b110 0
1-
b111 '
b111 (
b111 2
1&
#2800
0&
#3000
b1000 )
b1000 '
b1000 (
b1000 2
b111 $
b111 ,
b111 1
0-
1&
#3200
0&
#3400
b1000 %
b1000 +
b1000 0
1-
0!
b0 '
b0 (
b0 2
1&
