probadorDemux1x4_8Bits.v
module probadorDemux1x4_8Bits(
    output reg clk,
    output reg validIn,
    output reg [7:0] In,
    input outValid0,
    input outValid1,
    input outValid2,
    input outValid3,
    input [7:0]  data_out0,
    input [7:0]  data_out1,
    input [7:0]  data_out2,
    input [7:0]  data_out3 
);

	initial begin
		$dumpfile("Pruebademux1x4_8Bits.vcd");	
		$dumpvars;
		
		//$display ("\t\t\tclk,\tS,\tVal,\tin0,\tin1,\toutCon, \toutEstr,\tcont");
		
		//$monitor($time,"\t%b\t%b\t%b\t%b\t%b\t%b\t\t%b", clk, v);
		{In} =  8'b00000000;	// A los 2 bits, asigna un tipo bit con valor 0.
        {validIn} = 1'b1; 
		repeat (8) begin		
        		@(posedge clk);	// Espera/sincroniza con el flanco positivo del reloj
                
                {In} <= {In} +1;
                /*
				if(data_out_est==data_out_cond)
					checker<=1;
				else
					checker<=0;
                */
		end
		@(posedge clk);	
		{ validIn, In} <= 'b0;
		$finish;		
	end
	// Reloj
	initial	clk 	<= 0;	
	always	#20 clk 	<= ~clk;		// Hace "toggle" cada 20*10ns
endmodule

Demux_1x2_8Bits.v
module Demux_1x2_8Bits( 
        input [7:0] In0, 
        input clk, validIn, 
        output reg outValid0, outValid1,  
        output reg [7:0] data_out0,data_out1
        );

reg [7:0] ValorAnterior_out0;
reg [7:0] ValorAnterior_out1;
reg  validTemp_In0;
reg  validTemp_In1;
reg selector;

initial begin
        selector = 0;
end

always @(*)begin
        if(validIn == 1 && selector == 0) begin
            ValorAnterior_out0 =In0;
            validTemp_In0= validIn;

        end

        else if(validIn == 1 && selector == 1) begin
            ValorAnterior_out1 =In0;
            validTemp_In1 = validIn;
        end

end

always @(posedge clk)begin
        selector <= selector +1;       
        data_out0 <= ValorAnterior_out0;
        data_out1 <= ValorAnterior_out1;
        outValid0 <= validTemp_In0;
        outValid1 <= validTemp_In1;
end

endmodule

Demux_1x4_8Bits.v
`include "Demux_1x2_8Bits.v"

module Demux_1x4_8Bits(input [7:0] In, input clk, validIn, output validOut0, validOut1,validOut2,validOut3,  output  [7:0] data_out0,data_out1, data_out2,data_out3);
    wire [7:0] salida0Demux1, salida1Demux1;
    wire valid0Temp, valid1Temp;
    

    Demux_1x2_8Bits Demux1(.In0(In), .clk(clk), . validIn(validIn), .outValid0(valid0Temp), .outValid1(valid1Temp), .data_out0(salida0Demux1), .data_out1(salida1Demux1));
    Demux_1x2_8Bits Demux2(.In0(salida0Demux1), .clk(clk), . validIn(valid0Temp), .outValid0(validOut0), .outValid1(validOut1), .data_out0(data_out0), .data_out1(data_out1));
    Demux_1x2_8Bits Demux3(.In0(salida1Demux1), .clk(clk), . validIn(valid1Temp), .outValid0(validOut2), .outValid1(validOut3), .data_out0(data_out2), .data_out1(data_out3));
endmodule

BancoPruebaDemux1x4_8Bits.v
`timescale 	1ns				/ 100ps
`include "Demux_1x4_8Bits.v"
`include "probadorDemux1x4_8Bits.v"


module BancoPruebaDemux1x4_8Bits; // Testbench
	// Por lo general, las señales en el banco de pruebas son wires.
	// No almacenan un valor, son manejadas por otras instancias de módulos.
	wire clk, validIn, outvalid0, outvalid1, outvalid2, outvalid3;
    wire [7:0] In0, dataout0,dataout1, dataout2, dataout3;


    Demux_1x4_8Bits Demux_1x4( .In(In0), .clk(clk), .validIn(validIn), .validOut0(outvalid0), .validOut1(outvalid1), .validOut2(outvalid2), .validOut3(outvalid3),.data_out0(dataout0),.data_out1(dataout1),.data_out2(dataout2),.data_out3(dataout3));
  
	probadorDemux1x4_8Bits prob( .In(In0), .clk(clk), .validIn(validIn), .outValid0(outvalid0), .outValid1(outvalid1), .data_out0(dataout0),.data_out1(dataout1));
 
/*
	Mux4x1_4Bits Mux4x1Conductual( .valid(valid), .selector(selector), .data_in0(data_in0), .data_in1(data_in1), .data_in2(data_in2), .data_in3(data_in3), .data_out(data_outCond));
    Mux4x1_4Bits_synth Mux4x1Estructural( .valid(valid), .selector(selector), .data_in0(data_in0), .data_in1(data_in1), .data_in2(data_in2), .data_in3(data_in3), .data_out(data_outEstr));
	probador prob(.clk(clk), .valid(valid), .selector(selector), .data_in0(data_in0), .data_in1(data_in1),.data_in2(data_in2), .data_in3(data_in3), .data_outConductual(data_outCond), .data_outExtructural(data_outEstr));
  */  

endmodule

Pruebademux1x4_8Bits.vcd
$date
	Tue May 25 01:44:30 2021
$end
$version
	Icarus Verilog
$end
$timescale
	100ps
$end
$scope module BancoPruebaDemux1x4_8Bits $end
$var wire 1 ! validIn $end
$var wire 1 " outvalid3 $end
$var wire 1 # outvalid2 $end
$var wire 1 $ outvalid1 $end
$var wire 1 % outvalid0 $end
$var wire 8 & dataout3 [7:0] $end
$var wire 8 ' dataout2 [7:0] $end
$var wire 8 ( dataout1 [7:0] $end
$var wire 8 ) dataout0 [7:0] $end
$var wire 1 * clk $end
$var wire 8 + In0 [7:0] $end
$scope module Demux_1x4 $end
$var wire 1 " validOut3 $end
$var wire 1 # validOut2 $end
$var wire 1 $ validOut1 $end
$var wire 1 % validOut0 $end
$var wire 1 ! validIn $end
$var wire 1 , valid1Temp $end
$var wire 1 - valid0Temp $end
$var wire 8 . salida1Demux1 [7:0] $end
$var wire 8 / salida0Demux1 [7:0] $end
$var wire 8 0 data_out3 [7:0] $end
$var wire 8 1 data_out2 [7:0] $end
$var wire 8 2 data_out1 [7:0] $end
$var wire 8 3 data_out0 [7:0] $end
$var wire 1 * clk $end
$var wire 8 4 In [7:0] $end
$scope module Demux1 $end
$var wire 1 ! validIn $end
$var wire 1 * clk $end
$var wire 8 5 In0 [7:0] $end
$var reg 8 6 ValorAnterior_out0 [7:0] $end
$var reg 8 7 ValorAnterior_out1 [7:0] $end
$var reg 8 8 data_out0 [7:0] $end
$var reg 8 9 data_out1 [7:0] $end
$var reg 1 - outValid0 $end
$var reg 1 , outValid1 $end
$var reg 1 : selector $end
$var reg 1 ; validTemp_In0 $end
$var reg 1 < validTemp_In1 $end
$upscope $end
$scope module Demux2 $end
$var wire 8 = In0 [7:0] $end
$var wire 1 - validIn $end
$var wire 1 * clk $end
$var reg 8 > ValorAnterior_out0 [7:0] $end
$var reg 8 ? ValorAnterior_out1 [7:0] $end
$var reg 8 @ data_out0 [7:0] $end
$var reg 8 A data_out1 [7:0] $end
$var reg 1 % outValid0 $end
$var reg 1 $ outValid1 $end
$var reg 1 B selector $end
$var reg 1 C validTemp_In0 $end
$var reg 1 D validTemp_In1 $end
$upscope $end
$scope module Demux3 $end
$var wire 8 E In0 [7:0] $end
$var wire 1 , validIn $end
$var wire 1 * clk $end
$var reg 8 F ValorAnterior_out0 [7:0] $end
$var reg 8 G ValorAnterior_out1 [7:0] $end
$var reg 8 H data_out0 [7:0] $end
$var reg 8 I data_out1 [7:0] $end
$var reg 1 # outValid0 $end
$var reg 1 " outValid1 $end
$var reg 1 J selector $end
$var reg 1 K validTemp_In0 $end
$var reg 1 L validTemp_In1 $end
$upscope $end
$upscope $end
$scope module prob $end
$var wire 8 M data_out0 [7:0] $end
$var wire 8 N data_out1 [7:0] $end
$var wire 8 O data_out2 [7:0] $end
$var wire 8 P data_out3 [7:0] $end
$var wire 1 % outValid0 $end
$var wire 1 $ outValid1 $end
$var wire 1 Q outValid2 $end
$var wire 1 R outValid3 $end
$var reg 8 S In [7:0] $end
$var reg 1 * clk $end
$var reg 1 ! validIn $end
$upscope $end
$upscope $end
$enddefinitions $end
#0
$dumpvars
b0 S
zR
zQ
bz P
bz O
bx N
bx M
xL
xK
0J
bx I
bx H
bx G
bx F
bx E
xD
xC
0B
bx A
bx @
bx ?
bx >
bx =
x<
1;
0:
bx 9
bx 8
bx 7
b0 6
b0 5
b0 4
bx 3
bx 2
bx 1
bx 0
bx /
bx .
x-
x,
b0 +
0*
bx )
bx (
bx '
bx &
x%
x$
x#
x"
1!
$end
#200
1D
b0 ?
1<
b1 7
1-
b0 /
b0 8
b0 =
1:
1B
1J
b1 +
b1 4
b1 5
b1 S
1*
#400
0*
#600
1C
b0 >
1K
b1 F
b10 6
b10 +
b10 4
b10 5
b10 S
0J
1$
b0 (
b0 2
b0 A
b0 N
0B
1,
b1 .
b1 9
b1 E
0:
1*
#800
0*
#1000
b10 ?
1L
b1 G
b11 7
b10 /
b10 8
b10 =
1:
1%
b0 )
b0 3
b0 @
b0 M
1B
1#
b1 '
b1 1
b1 H
1J
b11 +
b11 4
b11 5
b11 S
1*
#1200
0*
#1400
b10 >
b11 F
b100 6
b100 +
b100 4
b100 5
b100 S
1"
b1 &
b1 0
b1 I
0J
b10 (
b10 2
b10 A
b10 N
0B
b11 .
b11 9
b11 E
0:
1*
#1600
0*
#1800
b100 ?
b11 G
b101 7
b100 /
b100 8
b100 =
1:
b10 )
b10 3
b10 @
b10 M
1B
b11 '
b11 1
b11 H
1J
b101 +
b101 4
b101 5
b101 S
1*
#2000
0*
#2200
b100 >
b101 F
b110 6
b110 +
b110 4
b110 5
b110 S
b11 &
b11 0
b11 I
0J
b100 (
b100 2
b100 A
b100 N
0B
b101 .
b101 9
b101 E
0:
1*
#2400
0*
#2600
b110 ?
b101 G
b111 7
b110 /
b110 8
b110 =
1:
b100 )
b100 3
b100 @
b100 M
1B
b101 '
b101 1
b101 H
1J
b111 +
b111 4
b111 5
b111 S
1*
#2800
0*
#3000
b110 >
b111 F
b1000 6
b1000 +
b1000 4
b1000 5
b1000 S
b101 &
b101 0
b101 I
0J
b110 (
b110 2
b110 A
b110 N
0B
b111 .
b111 9
b111 E
0:
1*
#3200
0*
#3400
b1000 ?
b111 G
b1000 /
b1000 8
b1000 =
1:
b110 )
b110 3
b110 @
b110 M
1B
b111 '
b111 1
b111 H
1J
0!
b0 +
b0 4
b0 5
b0 S
1*
