probadorRecirculacion.v
module probadorRecirculacion( // Módulo probador: generador de señales y monitor de datos
output reg clk,
output reg validIn,
output reg [7:0] In0,
output reg [7:0] In1,
output reg [7:0] In2,
output reg [7:0] In3,
input [7:0] data_Mux0,
input [7:0] data_Probador0,
input [7:0] data_Mux1,
input [7:0] data_Probador1,
input [7:0] data_Mux2,
input [7:0] data_Probador2,
input [7:0] data_Mux3,
input [7:0] data_Probador3
);

	initial begin
		$dumpfile("PruebaRecirculacionFelipeJOSERolo.vcd");	
		$dumpvars;
		
		//$display ("\t\t\tclk,\tS,\tVal,\tin0,\tin1,\toutCon, \toutEstr,\tcont");
		
		//$monitor($time,"\t%b\t%b\t%b\t%b\t%b\t%b\t\t%b", clk, v);
		{In0} =  8'b00000000;
        {In1} =  8'b00000000;
        {In2} =  8'b00000000;
        {In3} =  8'b00000000;	
        {validIn} = 1'b0; 
		repeat (8) begin		
        		@(posedge clk);	// Espera/sincroniza con el flanco positivo del reloj
                {validIn} <= {validIn} +1;
                {In0} <= {In0} +1;
                {In1} <= {In1} +1;
                {In2} <= {In2} +1;
                {In3} <= {In3} +1;
                /*
				if(data_out_est==data_out_cond)
					checker<=1;
				else
					checker<=0;
                */
		end
		@(posedge clk);	
		{ validIn, In0, In1, In2, In3} <= 'b0;
		$finish;		
	end
	// Reloj
	initial	clk 	<= 0;	
	always	#20 clk 	<= ~clk;		
endmodule

Recirculacion.v
module Recirculacion(
    input [7:0] In0, In1, In2, In3,
    input validIn, 
    output reg [7:0] data_mux0,
    output reg [7:0] data_Probador0,
    output reg [7:0] data_mux1,
    output reg [7:0] data_Probador1,
    output reg [7:0] data_mux2,
    output reg [7:0] data_Probador2, 
    output reg [7:0] data_mux3,
    output reg [7:0] data_Probador3
    );
//son 4 demuxes

//DEMUX 1
always @(*)begin
        if(validIn == 1 ) begin //de momento si selector es 1 continuamos sino mandamos al probador
            data_mux0 =In0;
        end

        else if(validIn == 0 )begin
            data_Probador0 =In0;
            data_mux0 = 8'b0;
        end

end

//DEMUX 2
always @(*)begin
        if(validIn == 1 ) begin //de momento si selector es 1 continuamos sino mandamos al probador
            data_mux1 =In1;
        end

        else if(validIn == 0 )begin
            data_Probador1 =In1;
            data_mux1 = 8'b0;
        end

end

//DEMUX 3
always @(*)begin
        if(validIn == 1 ) begin //de momento si selector es 1 continuamos sino mandamos al probador
            data_mux2 =In2;
        end

        else if(validIn == 0 )begin
            data_Probador2 =In2;
            data_mux2 = 8'b0;
        end

end

//DEMUX 4
always @(*)begin
        if(validIn == 1 ) begin //de momento si selector es 1 continuamos sino mandamos al probador
            data_mux3 =In3;
        end

        else if(validIn == 0 )begin
            data_Probador3 =In3;
            data_mux3 = 8'b0;
        end

end

endmodule

BancoPruebaRecirculacion.v
`timescale 	1ns				/ 100ps
`include "Recirculacion.v"
`include "probadorRecirculacion.v"


module BancoPruebaRecirculacion; // Testbench
	// Por lo general, las señales en el banco de pruebas son wires.
	// No almacenan un valor, son manejadas por otras instancias de módulos.
	wire clk, validIn;
    wire [7:0] In0,In1,In2,In3, data_Mux0, data_Probador0,data_Mux1, data_Probador1,data_Mux2, data_Probador2,data_Mux3, data_Probador3;


    Recirculacion ParteRecirculacion( .In0(In0), .In1(In1), .In2(In2), .In3(In3), .validIn(validIn), .data_mux0(data_Mux0), .data_Probador0(data_Probador0), .data_mux1(data_Mux1), .data_Probador1(data_Probador1), .data_mux2(data_Mux2), .data_Probador2(data_Probador2), .data_mux3(data_Mux3), .data_Probador3(data_Probador3));
  
	probadorRecirculacion prob( .In0(In0), .In1(In1), .In2(In2), .In3(In3), .validIn(validIn), .data_Mux0(data_Mux0), .data_Probador0(data_Probador0), .data_Mux1(data_Mux1), .data_Probador1(data_Probador1), .data_Mux2(data_Mux2), .data_Probador2(data_Probador2), .data_Mux3(data_Mux3), .data_Probador3(data_Probador3));
 
/*
	Mux4x1_4Bits Mux4x1Conductual( .valid(valid), .selector(selector), .data_in0(data_in0), .data_in1(data_in1), .data_in2(data_in2), .data_in3(data_in3), .data_out(data_outCond));
    Mux4x1_4Bits_synth Mux4x1Estructural( .valid(valid), .selector(selector), .data_in0(data_in0), .data_in1(data_in1), .data_in2(data_in2), .data_in3(data_in3), .data_out(data_outEstr));
	probador prob(.clk(clk), .valid(valid), .selector(selector), .data_in0(data_in0), .data_in1(data_in1),.data_in2(data_in2), .data_in3(data_in3), .data_outConductual(data_outCond), .data_outExtructural(data_outEstr));
  */  

endmodule

PruebaRecirculacionFelipeJOSERolo.vcd
$date
	Tue May 25 00:17:54 2021
$end
$version
	Icarus Verilog
$end
$timescale
	100ps
$end
$scope module BancoPruebaRecirculacion $end
$var wire 1 ! validIn $end
$var wire 8 " data_Probador3 [7:0] $end
$var wire 8 # data_Probador2 [7:0] $end
$var wire 8 $ data_Probador1 [7:0] $end
$var wire 8 % data_Probador0 [7:0] $end
$var wire 8 & data_Mux3 [7:0] $end
$var wire 8 ' data_Mux2 [7:0] $end
$var wire 8 ( data_Mux1 [7:0] $end
$var wire 8 ) data_Mux0 [7:0] $end
$var wire 8 * In3 [7:0] $end
$var wire 8 + In2 [7:0] $end
$var wire 8 , In1 [7:0] $end
$var wire 8 - In0 [7:0] $end
$scope module ParteRecirculacion $end
$var wire 1 ! validIn $end
$var wire 8 . In3 [7:0] $end
$var wire 8 / In2 [7:0] $end
$var wire 8 0 In1 [7:0] $end
$var wire 8 1 In0 [7:0] $end
$var reg 8 2 data_Probador0 [7:0] $end
$var reg 8 3 data_Probador1 [7:0] $end
$var reg 8 4 data_Probador2 [7:0] $end
$var reg 8 5 data_Probador3 [7:0] $end
$var reg 8 6 data_mux0 [7:0] $end
$var reg 8 7 data_mux1 [7:0] $end
$var reg 8 8 data_mux2 [7:0] $end
$var reg 8 9 data_mux3 [7:0] $end
$upscope $end
$scope module prob $end
$var wire 8 : data_Mux0 [7:0] $end
$var wire 8 ; data_Mux1 [7:0] $end
$var wire 8 < data_Mux2 [7:0] $end
$var wire 8 = data_Mux3 [7:0] $end
$var wire 8 > data_Probador0 [7:0] $end
$var wire 8 ? data_Probador1 [7:0] $end
$var wire 8 @ data_Probador2 [7:0] $end
$var wire 8 A data_Probador3 [7:0] $end
$var reg 8 B In0 [7:0] $end
$var reg 8 C In1 [7:0] $end
$var reg 8 D In2 [7:0] $end
$var reg 8 E In3 [7:0] $end
$var reg 1 F clk $end
$var reg 1 ! validIn $end
$upscope $end
$upscope $end
$enddefinitions $end
#0
$dumpvars
0F
b0 E
b0 D
b0 C
b0 B
b0 A
b0 @
b0 ?
b0 >
bx =
bx <
bx ;
bx :
bx 9
bx 8
bx 7
bx 6
b0 5
b0 4
b0 3
b0 2
b0 1
b0 0
b0 /
b0 .
b0 -
b0 ,
b0 +
b0 *
bx )
bx (
bx '
bx &
b0 %
b0 $
b0 #
b0 "
0!
$end
#200
b1 &
b1 9
b1 =
b1 '
b1 8
b1 <
b1 (
b1 7
b1 ;
b1 )
b1 6
b1 :
b1 *
b1 .
b1 E
b1 +
b1 /
b1 D
b1 ,
b1 0
b1 C
b1 -
b1 1
b1 B
1!
1F
#400
0F
#600
b10 "
b10 5
b10 A
b10 #
b10 4
b10 @
b10 $
b10 3
b10 ?
b10 %
b10 2
b10 >
b10 *
b10 .
b10 E
b10 +
b10 /
b10 D
b10 ,
b10 0
b10 C
b10 -
b10 1
b10 B
0!
1F
#800
0F
#1000
b11 &
b11 9
b11 =
b11 '
b11 8
b11 <
b11 (
b11 7
b11 ;
b11 )
b11 6
b11 :
b11 *
b11 .
b11 E
b11 +
b11 /
b11 D
b11 ,
b11 0
b11 C
b11 -
b11 1
b11 B
1!
1F
#1200
0F
#1400
b100 "
b100 5
b100 A
b100 #
b100 4
b100 @
b100 $
b100 3
b100 ?
b100 %
b100 2
b100 >
b100 *
b100 .
b100 E
b100 +
b100 /
b100 D
b100 ,
b100 0
b100 C
b100 -
b100 1
b100 B
0!
1F
#1600
0F
#1800
b101 &
b101 9
b101 =
b101 '
b101 8
b101 <
b101 (
b101 7
b101 ;
b101 )
b101 6
b101 :
b101 *
b101 .
b101 E
b101 +
b101 /
b101 D
b101 ,
b101 0
b101 C
b101 -
b101 1
b101 B
1!
1F
#2000
0F
#2200
b110 "
b110 5
b110 A
b110 #
b110 4
b110 @
b110 $
b110 3
b110 ?
b110 %
b110 2
b110 >
b110 *
b110 .
b110 E
b110 +
b110 /
b110 D
b110 ,
b110 0
b110 C
b110 -
b110 1
b110 B
0!
1F
#2400
0F
#2600
b111 &
b111 9
b111 =
b111 '
b111 8
b111 <
b111 (
b111 7
b111 ;
b111 )
b111 6
b111 :
b111 *
b111 .
b111 E
b111 +
b111 /
b111 D
b111 ,
b111 0
b111 C
b111 -
b111 1
b111 B
1!
1F
#2800
0F
#3000
b1000 "
b1000 5
b1000 A
b1000 #
b1000 4
b1000 @
b1000 $
b1000 3
b1000 ?
b1000 %
b1000 2
b1000 >
b1000 *
b1000 .
b1000 E
b1000 +
b1000 /
b1000 D
b1000 ,
b1000 0
b1000 C
b1000 -
b1000 1
b1000 B
0!
1F
#3200
0F
#3400
b0 %
b0 2
b0 >
b0 $
b0 3
b0 ?
b0 #
b0 4
b0 @
b0 "
b0 5
b0 A
b0 -
b0 1
b0 B
b0 ,
b0 0
b0 C
b0 +
b0 /
b0 D
b0 *
b0 .
b0 E
1F
