Recirculacion.v
module Recirculacion(
    input [7:0] In0, In1, In2, In3,
    input validIn, 
    output reg [7:0] data_mux0,
    output reg [7:0] data_Probador0,
    output reg [7:0] data_mux1,
    output reg [7:0] data_Probador1,
    output reg [7:0] data_mux2,
    output reg [7:0] data_Probador2, 
    output reg [7:0] data_mux3,
    output reg [7:0] data_Probador3
    );
//son 4 demuxes

//DEMUX 1
always @(*)begin
        if(validIn == 1 ) begin //de momento si selector es 1 continuamos sino mandamos al probador
            data_mux0 =In0;
        end

        else if(validIn == 0 )begin
            data_Probador0 =In0;
            data_mux0 = 8'b0;
        end

end

//DEMUX 2
always @(*)begin
        if(validIn == 1 ) begin //de momento si selector es 1 continuamos sino mandamos al probador
            data_mux1 =In1;
        end

        else if(validIn == 0 )begin
            data_Probador1 =In1;
            data_mux1 = 8'b0;
        end

end

//DEMUX 3
always @(*)begin
        if(validIn == 1 ) begin //de momento si selector es 1 continuamos sino mandamos al probador
            data_mux2 =In2;
        end

        else if(validIn == 0 )begin
            data_Probador2 =In2;
            data_mux2 = 8'b0;
        end

end

//DEMUX 4
always @(*)begin
        if(validIn == 1 ) begin //de momento si selector es 1 continuamos sino mandamos al probador
            data_mux3 =In3;
        end

        else if(validIn == 0 )begin
            data_Probador3 =In3;
            data_mux3 = 8'b0;
        end

end

endmodule

Mux2x1_8Bits.v
module Mux2x1_8Bits(
    input [7:0] In0,In1,
    input clk, valid0, valid1,
    output reg outValid,
    output reg [7:0] data_out
    );

    reg [7:0] ValorAnterior;
    reg  validTemp;
    reg selector=0;

   /* initial begin
        selector = 0;
        validTemp = 0;
        ValorAnterior = 0;
    end*/

    always @(*)begin
        //selector = 0;
        validTemp = 0;
        ValorAnterior = data_out;

        if(valid0 == 1 & selector == 0) begin
            ValorAnterior = In0;
            validTemp = valid0;
        end

        else if(valid1 == 1 & selector == 1) begin
            ValorAnterior = In1; 
            validTemp = valid1;  
        end
        else begin
            validTemp = 0;
            ValorAnterior = ValorAnterior;
        end
    end  

    always @(posedge clk)begin
        //selector <= 0;
        selector <= selector + 1;
        data_out <= ValorAnterior;
        outValid <= validTemp;
        
    end

endmodule

synth_phytx.v
/* Generated by Yosys 0.9 (git sha1 1979e0b) */
`include "cmos_cells.v"
(* src = "Mux2x1_8Bits.v:1" *)
module Mux2x1_8Bits_synth(In0, In1, clk, valid0, valid1, outValid, data_out);
  (* src = "Mux2x1_8Bits.v:38" *)
  wire _00_;
  (* src = "Mux2x1_8Bits.v:18" *)
  wire [7:0] _01_;
  (* src = "Mux2x1_8Bits.v:18" *)
  wire _02_;
  (* src = "Mux2x1_8Bits.v:40" *)
  (* unused_bits = "1 2 3 4 5 6 7 8 9 10 11 12 13 14 15 16 17 18 19 20 21 22 23 24 25 26 27 28 29 30 31" *)
  wire [31:0] _03_;
  (* src = "Mux2x1_8Bits.v:23" *)
  wire _04_;
  (* src = "Mux2x1_8Bits.v:28" *)
  wire _05_;
  (* src = "Mux2x1_8Bits.v:23" *)
  wire _06_;
  (* src = "Mux2x1_8Bits.v:2" *)
  input [7:0] In0;
  (* src = "Mux2x1_8Bits.v:2" *)
  input [7:0] In1;
  (* src = "Mux2x1_8Bits.v:8" *)
  wire [7:0] ValorAnterior;
  (* src = "Mux2x1_8Bits.v:3" *)
  input clk;
  (* src = "Mux2x1_8Bits.v:5" *)
  output [7:0] data_out;
  reg [7:0] data_out;
  (* src = "Mux2x1_8Bits.v:4" *)
  output outValid;
  reg outValid;
  (* init = 1'h0 *)
  (* src = "Mux2x1_8Bits.v:10" *)
  reg selector = 1'h0;
  (* src = "Mux2x1_8Bits.v:3" *)
  input valid0;
  (* src = "Mux2x1_8Bits.v:3" *)
  input valid1;
  (* src = "Mux2x1_8Bits.v:9" *)
  wire validTemp;
  assign { _03_[31:1], _00_ } = selector + (* src = "Mux2x1_8Bits.v:40" *) 32'd1;
  assign _04_ = valid0 & (* src = "Mux2x1_8Bits.v:23" *) _06_;
  assign _05_ = valid1 & (* src = "Mux2x1_8Bits.v:28" *) selector;
  assign _06_ = ~ (* src = "Mux2x1_8Bits.v:23" *) selector;
  always @(posedge clk)
      data_out <= ValorAnterior;
  always @(posedge clk)
      outValid <= validTemp;
  always @(posedge clk)
      selector <= _00_;
  assign validTemp = _04_ ? (* full_case = 32'd1 *) (* src = "Mux2x1_8Bits.v:23" *) valid0 : _02_;
  assign ValorAnterior = _04_ ? (* full_case = 32'd1 *) (* src = "Mux2x1_8Bits.v:23" *) In0 : _01_;
  assign _02_ = _05_ ? (* full_case = 32'd1 *) (* src = "Mux2x1_8Bits.v:28" *) valid1 : 1'h0;
  assign _01_ = _05_ ? (* full_case = 32'd1 *) (* src = "Mux2x1_8Bits.v:28" *) In1 : data_out;
  assign _03_[0] = _00_;
endmodule

(* src = "Recirculacion.v:1" *)
module Recirculacion_synth(In0, In1, In2, In3, validIn, data_mux0, data_Probador0, data_mux1, data_Probador1, data_mux2, data_Probador2, data_mux3, data_Probador3);
  (* src = "Recirculacion.v:2" *)
  input [7:0] In0;
  (* src = "Recirculacion.v:2" *)
  input [7:0] In1;
  (* src = "Recirculacion.v:2" *)
  input [7:0] In2;
  (* src = "Recirculacion.v:2" *)
  input [7:0] In3;
  (* src = "Recirculacion.v:5" *)
  output [7:0] data_Probador0;
  (* src = "Recirculacion.v:7" *)
  output [7:0] data_Probador1;
  (* src = "Recirculacion.v:9" *)
  output [7:0] data_Probador2;
  (* src = "Recirculacion.v:11" *)
  output [7:0] data_Probador3;
  (* src = "Recirculacion.v:4" *)
  output [7:0] data_mux0;
  (* src = "Recirculacion.v:6" *)
  output [7:0] data_mux1;
  (* src = "Recirculacion.v:8" *)
  output [7:0] data_mux2;
  (* src = "Recirculacion.v:10" *)
  output [7:0] data_mux3;
  (* src = "Recirculacion.v:3" *)
  input validIn;
  assign data_mux3 = validIn ? (* full_case = 32'd1 *) (* src = "Recirculacion.v:64" *) In3 : 8'h00;
  assign data_Probador3 = validIn ? (* full_case = 32'd1 *) (* src = "Recirculacion.v:64" *) 8'h00 : In3;
  assign data_mux2 = validIn ? (* full_case = 32'd1 *) (* src = "Recirculacion.v:49" *) In2 : 8'h00;
  assign data_Probador2 = validIn ? (* full_case = 32'd1 *) (* src = "Recirculacion.v:49" *) 8'h00 : In2;
  assign data_mux1 = validIn ? (* full_case = 32'd1 *) (* src = "Recirculacion.v:34" *) In1 : 8'h00;
  assign data_Probador1 = validIn ? (* full_case = 32'd1 *) (* src = "Recirculacion.v:34" *) 8'h00 : In1;
  assign data_mux0 = validIn ? (* full_case = 32'd1 *) (* src = "Recirculacion.v:19" *) In0 : 8'h00;
  assign data_Probador0 = validIn ? (* full_case = 32'd1 *) (* src = "Recirculacion.v:19" *) 8'h00 : In0;
endmodule

(* top =  1  *)
(* src = "phy_tx.v:4" *)
module phy_tx_synth(In0, In1, In2, In3, clk, clk2, clk4, valid0, valid1, valid2, valid3, validIn, data_out, valid_out, data_Probador0, data_Probador1, data_Probador2, data_Probador3);
  (* src = "phy_tx.v:5" *)
  input [7:0] In0;
  (* src = "phy_tx.v:29" *)
  wire [7:0] In0_good;
  (* src = "phy_tx.v:6" *)
  input [7:0] In1;
  (* src = "phy_tx.v:29" *)
  wire [7:0] In1_good;
  (* src = "phy_tx.v:7" *)
  input [7:0] In2;
  (* src = "phy_tx.v:29" *)
  wire [7:0] In2_good;
  (* src = "phy_tx.v:8" *)
  input [7:0] In3;
  (* src = "phy_tx.v:29" *)
  wire [7:0] In3_good;
  (* src = "phy_tx.v:9" *)
  input clk;
  (* src = "phy_tx.v:10" *)
  input clk2;
  (* src = "phy_tx.v:11" *)
  input clk4;
  (* src = "phy_tx.v:18" *)
  output [7:0] data_Probador0;
  (* src = "phy_tx.v:19" *)
  output [7:0] data_Probador1;
  (* src = "phy_tx.v:20" *)
  output [7:0] data_Probador2;
  (* src = "phy_tx.v:21" *)
  output [7:0] data_Probador3;
  (* src = "phy_tx.v:14" *)
  output [7:0] data_out;
  (* src = "phy_tx.v:26" *)
  wire [7:0] out_temp1;
  (* src = "phy_tx.v:26" *)
  wire [7:0] out_temp2;
  (* src = "phy_tx.v:12" *)
  input valid0;
  (* src = "phy_tx.v:12" *)
  input valid1;
  (* src = "phy_tx.v:12" *)
  input valid2;
  (* src = "phy_tx.v:12" *)
  input valid3;
  (* src = "phy_tx.v:13" *)
  input validIn;
  (* src = "phy_tx.v:15" *)
  output valid_out;
  (* src = "phy_tx.v:27" *)
  wire valid_out_1;
  (* src = "phy_tx.v:27" *)
  wire valid_out_2;
  (* module_not_derived = 32'd1 *)
  (* src = "phy_tx.v:56" *)
  Mux2x1_8Bits MUX2x1_1 (
    .In0(In0_good),
    .In1(In1_good),
    .clk(clk2),
    .data_out(out_temp1),
    .outValid(valid_out_1),
    .valid0(valid0),
    .valid1(valid1)
  );
  (* module_not_derived = 32'd1 *)
  (* src = "phy_tx.v:66" *)
  Mux2x1_8Bits MUX2x1_2 (
    .In0(In2_good),
    .In1(In3_good),
    .clk(clk2),
    .data_out(out_temp2),
    .outValid(valid_out_2),
    .valid0(valid2),
    .valid1(valid3)
  );
  (* module_not_derived = 32'd1 *)
  (* src = "phy_tx.v:81" *)
  Mux2x1_8Bits MUX2x1_3 (
    .In0(out_temp2),
    .In1(out_temp1),
    .clk(clk4),
    .data_out(data_out),
    .outValid(valid_out),
    .valid0(valid_out_2),
    .valid1(valid_out_1)
  );
  (* module_not_derived = 32'd1 *)
  (* src = "phy_tx.v:32" *)
  Recirculacion Recirculacion_testbench (
    .In0(In0),
    .In1(In1),
    .In2(In2),
    .In3(In3),
    .data_Probador0(data_Probador0),
    .data_Probador1(data_Probador1),
    .data_Probador2(data_Probador2),
    .data_Probador3(data_Probador3),
    .data_mux0(In0_good),
    .data_mux1(In1_good),
    .data_mux2(In2_good),
    .data_mux3(In3_good),
    .validIn(validIn)
  );
endmodule

Probador_phy_tx.v
module Probador_phy_tx(
    output reg [7:0] In0,
    output reg [7:0] In1,
    output reg [7:0] In2,
    output reg [7:0] In3,
    output reg clk,
    output reg clk2,
    output reg clk4,
    output reg valid0, valid1, valid2, valid3,
    input [7:0] data_out,

    ///// Reciclación

    input [7:0] data_Probador0,
    input [7:0] data_Probador1,
    input [7:0] data_Probador2,
    input [7:0] data_Probador3,
    input valid_out,
    output reg validIn 
);

initial begin
        // Nombre de archivo del "dump"
		$dumpfile("phytxFINAL.vcd");

        // Directiva para "dumpear" variables	
		$dumpvars;	

        //Mux 2x1 8bits
        @(posedge clk);
        validIn <= 1'b1;
        In0 <= 8'b11111111; 
        In1 <= 8'b11101110;
        In2 <= 8'b11011101;
        In3 <= 8'b11001100;
        valid0 <= 1'b1;
        valid1 <= 1'b1;
        valid2 <= 1'b1;
        valid3 <= 1'b1;
        	
       @(posedge clk);	
            
        In0 <= 8'b10111011; 
        In1 <= 8'b10101010;
        In2 <= 8'b10011001;
        In3 <= 8'b10001000; 

		@(posedge clk);

        valid0 <= 1'b0;
        valid1 <= 1'b0;
        valid3 <= 1'b0;
        In0 <= 8'b1010101; 
        In1 <= 8'b1010101;
        In2 <= 8'b1110111;
        In3 <= 8'b1010101; 
        @(posedge clk);
        valid2 <= 1'b0;
        @(posedge clk);


        ///// Prueba Circulación

        validIn <= 1'b0;
        In0 <= 8'b11111111; 
        In1 <= 8'b11101110;
        In2 <= 8'b11011101;
        In3 <= 8'b11001100;
        valid0 <= 1'b1;
        valid1 <= 1'b1;
        valid2 <= 1'b1;
        valid3 <= 1'b1;
        @(posedge clk);
        In0 <= 8'b10111011; 
        In1 <= 8'b10101010;
        In2 <= 8'b10011001;
        In3 <= 8'b10001000; 
		@(posedge clk);


         //Mux 2x1 8bits
        In0 <= 8'b00000000;
        In1 <= 8'b00000000; 
        In2 <= 8'b00000000; 
        In3 <= 8'b00000000;
        @(posedge clk);
        // Termina de almacenar señales
		$finish;

	end

	// Reloj

    //Valor inicial del reloj para que no sea indeterminado
	initial	clk 	<= 0;
    initial	clk2 	<= 1;	
    initial	clk4 	<= 1;

    //Toggle cada 2*10 nano segundos		
	always	#8 clk 	<= ~clk;

    always  #4 clk2 <= ~clk2;

    always  #2 clk4 <= ~clk4;
    		
endmodule

phy_tx.v
`include "Mux2x1_8Bits.v"
`include "Recirculacion.v"

module phy_tx(
    input [7:0] In0,
    input [7:0] In1,
    input [7:0] In2,
    input [7:0] In3,
    input clk,
    input clk2,
    input clk4,
    input valid0, valid1, valid2, valid3,
    input validIn, 
    output [7:0] data_out,
    output valid_out,

    ///// AL PROBADOR
    output [7:0] data_Probador0,
    output [7:0] data_Probador1,
    output [7:0] data_Probador2,
    output [7:0] data_Probador3


);

wire [7:0] out_temp1, out_temp2;
wire valid_out_1, valid_out_2;

wire [7:0] In0_good, In1_good, In2_good, In3_good;
////////////// Recirculación

Recirculacion Recirculacion_testbench (
    .In0(In0),
    .In1(In1),
    .In2(In2),
    .In3(In3),
    .validIn(validIn),
    .data_mux0(In0_good),
    .data_Probador0(data_Probador0),
    .data_mux1(In1_good),
    .data_Probador1(data_Probador1),
    .data_mux2(In2_good),
    .data_Probador2(data_Probador2), 
    .data_mux3(In3_good),
    .data_Probador3(data_Probador3)
);





////////////// Multiplexores

///// L1

Mux2x1_8Bits MUX2x1_1 (
    .In0(In0_good),
    .In1(In1_good),
    .clk(clk2),
    .valid0(valid0),
    .valid1(valid1),
    .outValid(valid_out_1),
    .data_out(out_temp1)
); 

Mux2x1_8Bits MUX2x1_2 (
    .In0(In2_good),
    .In1(In3_good),
    .clk(clk2),
    .valid0(valid2),
    .valid1(valid3),
    .outValid(valid_out_2),
    .data_out(out_temp2)
); 



///// L2


Mux2x1_8Bits MUX2x1_3 (
    .In0(out_temp2),
    .In1(out_temp1),
    .clk(clk4),
    .valid0(valid_out_2),
    .valid1(valid_out_1),
    .data_out(data_out),
    .outValid(valid_out)
); 


endmodule

BancoPruebas_phy_tx.v
`include "synth_phytx.v"
`include "phy_tx.v"
`include "Probador_phy_tx.v"

module BancoPruebas_phy_tx;

/*AUTOWIRE*/
// Beginning of automatic wires (for undeclared instantiated-module outputs)
wire [7:0]		In0;			// From Probador_phy_tx_testbench of Probador_phy_tx.v
wire [7:0]		In1;			// From Probador_phy_tx_testbench of Probador_phy_tx.v
wire [7:0]		In2;			// From Probador_phy_tx_testbench of Probador_phy_tx.v
wire [7:0]		In3;			// From Probador_phy_tx_testbench of Probador_phy_tx.v
wire			clk;			// From Probador_phy_tx_testbench of Probador_phy_tx.v
wire			clk2;			// From Probador_phy_tx_testbench of Probador_phy_tx.v
wire			clk4;			// From Probador_phy_tx_testbench of Probador_phy_tx.v
wire [7:0]		data_Probador0;		// From phy_tx_testbench of phy_tx.v
wire [7:0]		data_Probador1;		// From phy_tx_testbench of phy_tx.v
wire [7:0]		data_Probador2;		// From phy_tx_testbench of phy_tx.v
wire [7:0]		data_Probador3;		// From phy_tx_testbench of phy_tx.v
wire [7:0]		data_outC;
wire [7:0]		data_outE;		// From phy_tx_testbench of phy_tx.v
wire			valid0;			// From Probador_phy_tx_testbench of Probador_phy_tx.v
wire			valid1;			// From Probador_phy_tx_testbench of Probador_phy_tx.v
wire			valid2;			// From Probador_phy_tx_testbench of Probador_phy_tx.v
wire			valid3;			// From Probador_phy_tx_testbench of Probador_phy_tx.v
wire			validIn;		// From Probador_phy_tx_testbench of Probador_phy_tx.v
wire			valid_out;		// From phy_tx_testbench of phy_tx.v
// End of automatics

phy_tx phy_tx_testbench(/*AUTOINST*/
			// Outputs
			.data_out	(data_outC[7:0]),
			.valid_out	(valid_out),
			.data_Probador0	(data_Probador0[7:0]),
			.data_Probador1	(data_Probador1[7:0]),
			.data_Probador2	(data_Probador2[7:0]),
			.data_Probador3	(data_Probador3[7:0]),
			// Inputs
			.In0		(In0[7:0]),
			.In1		(In1[7:0]),
			.In2		(In2[7:0]),
			.In3		(In3[7:0]),
			.clk		(clk),
			.clk2		(clk2),
			.clk4		(clk4),
			.valid0		(valid0),
			.valid1		(valid1),
			.valid2		(valid2),
			.valid3		(valid3),
			.validIn	(validIn));

Probador_phy_tx Probador_phy_tx_testbench(/*AUTOINST*/
					  // Outputs
					  .In0			(In0[7:0]),
					  .In1			(In1[7:0]),
					  .In2			(In2[7:0]),
					  .In3			(In3[7:0]),
					  .clk			(clk),
					  .clk2			(clk2),
					  .clk4			(clk4),
					  .valid0		(valid0),
					  .valid1		(valid1),
					  .valid2		(valid2),
					  .valid3		(valid3),
					  .validIn		(validIn),
					  // Inputs
					  //.data_out		(data_out[7:0]),
					  .data_Probador0	(data_Probador0[7:0]),
					  .data_Probador1	(data_Probador1[7:0]),
					  .data_Probador2	(data_Probador2[7:0]),
					  .data_Probador3	(data_Probador3[7:0]),
					  .valid_out		(valid_out));


//EStructural					  
phy_tx_synth estructural(
 					  // Outputs
					  .In0			(In0[7:0]),
					  .In1			(In1[7:0]),
					  .In2			(In2[7:0]),
					  .In3			(In3[7:0]),
					  .clk			(clk),
					  .clk2			(clk2),
					  .clk4			(clk4),
					  .valid0		(valid0),
					  .valid1		(valid1),
					  .valid2		(valid2),
					  .valid3		(valid3),
					  .validIn		(validIn),
					  // Inputs
					  .data_out		(data_outE[7:0]),
					  .data_Probador0	(data_Probador0[7:0]),
					  .data_Probador1	(data_Probador1[7:0]),
					  .data_Probador2	(data_Probador2[7:0]),
					  .data_Probador3	(data_Probador3[7:0]),
					  .valid_out		(valid_out));
 
  


endmodule

// Local Variable:
   // eval:(verilog-read-defines)
   // eval:(verilog-read-includes)
   // End:

simulacion_phy.vcd
$date
	Tue May 25 15:27:38 2021
$end
$version
	GTKWave Analyzer v3.3.104 (w)1999-2020 BSI
$end
$timescale
	1 s
$end
$scope module BancoPruebas_phy_tx $end
$var wire 1 % validIn $end
$var wire 1 ) valid3 $end
$var wire 1 * valid_out $end
$var wire 1 ( valid2 $end
$var wire 1 ' valid1 $end
$var wire 1 & valid0 $end
$var wire 8 + data_out[7:0] $end
$var wire 1 $ clk4 $end
$var wire 1 # clk2 $end
$var wire 1 " clk $end
$upscope $end
$enddefinitions $end
#0
$dumpvars
bx +
x'
x(
x%
x)
1#
1$
x&
0"
0*
$end
#2
0$
#4
1$
0#
#6
0$
#8
1$
1#
1(
1'
1)
1%
1"
1&
#10
0$
#12
1$
0#
#14
0$
#16
1$
1#
0"
#18
0$
#20
1$
b11111111 +
0#
1*
#22
0$
#24
1$
1"
1#
b11011101 +
#26
0$
#28
1$
b11101110 +
0#
#30
0$
#32
1$
1#
b11001100 +
0"
#34
0$
#36
1$
b10111011 +
0#
#38
0$
#40
1$
1"
0&
0)
0'
1#
b10011001 +
#42
0$
#44
1$
b10101010 +
0#
#46
0$
#48
1$
1#
0"
b10001000 +
#50
0$
#52
1$
0#
0*
#54
0$
#56
1$
1*
1#
b1110111 +
0(
1"
#58
0$
#60
1$
0*
0#
#62
0$
#64
1$
1#
0"
#66
0$
#68
1$
0#
#70
0$
#72
1$
1#
1"
1)
1&
1(
1'
0%
#74
0$
#76
1$
0#
#78
0$
#80
1$
1#
0"
#82
0$
#84
1$
b0 +
0#
1*
