Serial-Paralelo/serial_paralelo.v
module serial_paralelo(
    input clk_4f, clk_32f, data_in,
    output reg [7:0] data2send,
    output reg [3:0] BC_counter,
    output reg active, valid_out);

    reg temp0, temp1, temp2, temp3, temp4, temp5, temp6, temp7;
    reg in_temp;
    reg [2:0] selector=3;
    reg [7:0] data_out;
   
 always@(selector)begin  
   case(selector) 
    0: temp7 = data_in;
                   
    1: temp6 = data_in;
    
    2: temp5 = data_in;
    
    3: temp4 = data_in;
    
    4: temp3 = data_in;
    
    5: temp2 = data_in;
    
    6: temp1 = data_in;
    
    7: temp0 = data_in;

    endcase
 end

always@(posedge clk_32f)begin
    selector<=selector+1;

end

always@(posedge clk_4f)begin

    data2send[0] <= temp0;
    data2send[1] <= temp1;
    data2send[2] <= temp2;
    data2send[3] <= temp3;
    data2send[4] <= temp4;
    data2send[5] <= temp5;
    data2send[6] <= temp6;
    data2send[7] <= temp7;

end


endmodule

Serial-Paralelo/probador_serial.v
module probador_serial(
    input [7:0] data2send, data_out,
    input [3:0] BC_counter,
    input active, valid_out,

    output reg clk_4f, clk_32f, data_in);

	initial begin
		$dumpfile("SerialParalelo.vcd");	
		$dumpvars;

        @(posedge clk_4f)
//PRIMER 00*************************************
        

        @(posedge clk_32f)
        {data_in} = 0;

        @(posedge clk_32f)
        {data_in} = 0;

        @(posedge clk_32f)
        {data_in} = 0;

        @(posedge clk_32f)
        {data_in} = 0;

        @(posedge clk_32f)
        {data_in} = 0;

        @(posedge clk_32f)
        {data_in} = 0;    

        @(posedge clk_32f)
        {data_in} = 0;

//SEGUBDO BC*************************************
        
        @(posedge clk_32f)
        {data_in} = 1;

        @(posedge clk_32f)
        {data_in} = 0;

        @(posedge clk_32f)
        {data_in} = 1;

        @(posedge clk_32f)
        {data_in} = 1;

        @(posedge clk_32f)
        {data_in} = 1;

        @(posedge clk_32f)
        {data_in} = 1;

        @(posedge clk_32f)
        {data_in} = 0;    

        @(posedge clk_32f)
        {data_in} = 0;


//TERCER BC*************************************
        @(posedge clk_32f)
        {data_in} = 1;

        @(posedge clk_32f)
        {data_in} = 0;

        @(posedge clk_32f)
        {data_in} = 1;

        @(posedge clk_32f)
        {data_in} = 1;

        @(posedge clk_32f)
        {data_in} = 1;

        @(posedge clk_32f)
        {data_in} = 1;

        @(posedge clk_32f)
        {data_in} = 0;    

        @(posedge clk_32f)
        {data_in} = 0;

//CUARTO BC*************************************
        @(posedge clk_32f)
        {data_in} = 1;

        @(posedge clk_32f)
        {data_in} = 0;

        @(posedge clk_32f)
        {data_in} = 1;

        @(posedge clk_32f)
        {data_in} = 1;

        @(posedge clk_32f)
        {data_in} = 1;

        @(posedge clk_32f)
        {data_in} = 1;

        @(posedge clk_32f)
        {data_in} = 0;    

        @(posedge clk_32f)
        {data_in} = 0;

//PRIMER FF*********************************

        @(posedge clk_32f)
        {data_in} = 1;

        @(posedge clk_32f)
        {data_in} = 1;

        @(posedge clk_32f)
        {data_in} = 1;

        @(posedge clk_32f)
        {data_in} = 1;

        @(posedge clk_32f)
        {data_in} = 1;

        @(posedge clk_32f)
        {data_in} = 1;

        @(posedge clk_32f)
        {data_in} = 1;    

        @(posedge clk_32f)
        {data_in} = 1;




//PRIMER EE
        @(posedge clk_32f)
        {data_in} = 1;

        @(posedge clk_32f)
        {data_in} = 1;

        @(posedge clk_32f)
        {data_in} = 1;

        @(posedge clk_32f)
        {data_in} = 0;

        @(posedge clk_32f)
        {data_in} = 1;

        @(posedge clk_32f)
        {data_in} = 1;

        @(posedge clk_32f)
        {data_in} = 1;    

        @(posedge clk_32f)
        {data_in} = 0;

        @(posedge clk_32f)

        $finish;

    end

    initial clk_4f <=0;
    initial clk_32f <= 0;

    always #64 clk_4f <= ~clk_4f;
    always #8 clk_32f <= ~clk_32f;


endmodule

Serial-Paralelo/BancoPruebasSerialParalelo.v
`include "probador_serial.v"
`include "serial_paralelo.v"

module BancoPruebasSerialParalelo;

wire clk_4f, clk_32f;
wire [7:0] data2send;
wire [3:0] BC_counter;
wire active, valid_out, data_in;

probador_serial probador(.clk_4f    (clk_4f), 
                                 .clk_32f   ( clk_32f),
                                 .data_in   (data_in),
                                 .data2send (data2send),
                                 .BC_counter    (BC_counter),
                                 .active    (active),
                                 .valid_out     (valid_out));


serial_paralelo SP(.clk_4f  (clk_4f), 
                   .clk_32f (clk_32f),
                   .data_in (data_in),
                   .data2send   (data2send),
                   .BC_counter  (BC_counter),
                   .active  (active),
                   .valid_out   (valid_out));

endmodule


// Local Variabes:
    // eval:(verilog-read-defines)
    // eval:(verilog-read-includes)
    // End:

Serial-Paralelo/SerialParalelo.vcd
$date
	Mon May 31 22:46:50 2021
$end
$version
	Icarus Verilog
$end
$timescale
	1s
$end
$scope module BancoPruebasSerialParalelo $end
$var wire 1 ! valid_out $end
$var wire 1 " data_in $end
$var wire 8 # data2send [7:0] $end
$var wire 1 $ clk_4f $end
$var wire 1 % clk_32f $end
$var wire 1 & active $end
$var wire 4 ' BC_counter [3:0] $end
$scope module SP $end
$var wire 1 " data_in $end
$var wire 1 $ clk_4f $end
$var wire 1 % clk_32f $end
$var reg 4 ( BC_counter [3:0] $end
$var reg 1 & active $end
$var reg 8 ) data2send [7:0] $end
$var reg 3 * selector [2:0] $end
$var reg 1 + temp0 $end
$var reg 1 , temp1 $end
$var reg 1 - temp2 $end
$var reg 1 . temp3 $end
$var reg 1 / temp4 $end
$var reg 1 0 temp5 $end
$var reg 1 1 temp6 $end
$var reg 1 2 temp7 $end
$var reg 1 ! valid_out $end
$upscope $end
$scope module probador $end
$var wire 4 3 BC_counter [3:0] $end
$var wire 1 & active $end
$var wire 8 4 data2send [7:0] $end
$var wire 8 5 data_out [7:0] $end
$var wire 1 ! valid_out $end
$var reg 1 % clk_32f $end
$var reg 1 $ clk_4f $end
$var reg 1 " data_in $end
$upscope $end
$upscope $end
$enddefinitions $end
#0
$dumpvars
bz 5
bx 4
bx 3
x2
x1
x0
x/
x.
x-
x,
x+
b11 *
bx )
bx (
bx '
x&
0%
0$
bx #
x"
x!
$end
#8
b100 *
1%
#16
0%
#24
b101 *
1%
#32
0%
#40
b110 *
1%
#48
0%
#56
b111 *
1%
#64
0%
1$
#72
02
b0 *
0"
1%
#80
0%
#88
01
b1 *
1%
#96
0%
#104
00
b10 *
1%
#112
0%
#120
0/
b11 *
1%
#128
0%
0$
#136
0.
b100 *
1%
#144
0%
#152
0-
b101 *
1%
#160
0%
#168
0,
b110 *
1%
#176
0%
#184
1+
b111 *
1"
1%
#192
b1 #
b1 )
b1 4
0%
1$
#200
b0 *
0"
1%
#208
0%
#216
11
b1 *
1"
1%
#224
0%
#232
10
b10 *
1%
#240
0%
#248
1/
b11 *
1%
#256
0%
0$
#264
1.
b100 *
1%
#272
0%
#280
b101 *
0"
1%
#288
0%
#296
b110 *
1%
#304
0%
#312
b111 *
1"
1%
#320
b1111001 #
b1111001 )
b1111001 4
0%
1$
#328
b0 *
0"
1%
#336
0%
#344
b1 *
1"
1%
#352
0%
#360
b10 *
1%
#368
0%
#376
b11 *
1%
#384
0%
0$
#392
b100 *
1%
#400
0%
#408
b101 *
0"
1%
#416
0%
#424
b110 *
1%
#432
0%
#440
b111 *
1"
1%
#448
0%
1$
#456
b0 *
0"
1%
#464
0%
#472
b1 *
1"
1%
#480
0%
#488
b10 *
1%
#496
0%
#504
b11 *
1%
#512
0%
0$
#520
b100 *
1%
#528
0%
#536
b101 *
0"
1%
#544
0%
#552
b110 *
1%
#560
0%
#568
b111 *
1"
1%
#576
0%
1$
#584
12
b0 *
1%
#592
0%
#600
b1 *
1%
#608
0%
#616
b10 *
1%
#624
0%
#632
b11 *
1%
#640
0%
0$
#648
b100 *
1%
#656
0%
#664
1-
b101 *
1%
#672
0%
#680
1,
b110 *
1%
#688
0%
#696
b111 *
1%
#704
b11111111 #
b11111111 )
b11111111 4
0%
1$
#712
b0 *
1%
#720
0%
#728
b1 *
1%
#736
0%
#744
00
b10 *
0"
1%
#752
0%
#760
b11 *
1"
1%
#768
0%
0$
#776
b100 *
1%
#784
0%
#792
b101 *
1%
#800
0%
#808
0,
b110 *
0"
1%
#816
0%
#824
0+
b111 *
1%
